setup.py
imageregistration/__init__.py
imageregistration.egg-info/PKG-INFO
imageregistration.egg-info/SOURCES.txt
imageregistration.egg-info/dependency_links.txt
imageregistration.egg-info/not-zip-safe
imageregistration.egg-info/top_level.txt