Metadata-Version: 1.0
Name: imageregistration
Version: 0.6
Summary: tools for image registration
Home-page: https://github.com/computational-humanities/topoi/blob/master/projects/topoi/
Author: Gordon Fischer
Author-email: gordon-fischer@gmx.de
License: Free
Platform: UNKNOWN
